{
  "carvers": [],
  "downfall": 0.5,
  "effects": {
    "fog_color": 10518688,
    "mood_sound": {
      "block_search_extent": 8,
      "offset": 2.0,
      "sound": "minecraft:ambient.cave",
      "tick_delay": 6000
    },
    "sky_color": 0,
    "water_color": 4159204,
    "water_fog_color": 329011
  },
  "features": [
    [],
    [],
    [],
    [],
    [],
    [],
    [],
    [],
    [],
    [],
    [
      "xray_world:y0",
      "xray_world:y16",
      "xray_world:y32",
      "xray_world:y48",
      "xray_world:y64",
      "xray_world:y80",
      "xray_world:y96",
      "xray_world:y112",
      "xray_world:y128",
      "xray_world:y144",
      "xray_world:y160",
      "xray_world:y176",
      "xray_world:y192",
      "xray_world:y208",
      "xray_world:y224",
      "xray_world:y240"
    ]
  ],
  "has_precipitation": false,
  "spawn_costs": {},
  "spawners": {
    "ambient": [],
    "axolotls": [],
    "creature": [],
    "misc": [],
    "monster": [
      {
        "maxCount": 4,
        "minCount": 4,
        "type": "minecraft:enderman",
        "weight": 10
      }
    ],
    "underground_water_creature": [],
    "water_ambient": [],
    "water_creature": []
  },
  "temperature": 0.5
}